crossdomainmedia/__init__.py
crossdomainmedia/auth.py
crossdomainmedia/utils.py
crossdomainmedia/views.py
django_crossdomainmedia-0.0.4.dist-info/LICENSE
django_crossdomainmedia-0.0.4.dist-info/METADATA
django_crossdomainmedia-0.0.4.dist-info/WHEEL
django_crossdomainmedia-0.0.4.dist-info/top_level.txt
django_crossdomainmedia-0.0.4.dist-info/RECORD
